tes_shopify/__init__.py
tes_shopify/client.py
tes_shopify/resources.py
tes_shopify/shopify_utils.py
python_tes_shopify-1.2.0.dist-info/METADATA
python_tes_shopify-1.2.0.dist-info/WHEEL
python_tes_shopify-1.2.0.dist-info/licenses/LICENSE
python_tes_shopify-1.2.0.dist-info/RECORD
