Metadata-Version: 2.1
Name: python_tes_shopify
Version: 1.2.0
Summary: Python TES Business Objects
Author-email: Johannes Eimer <johannes.eimer@jep-dev.com>
License-Expression: MIT
License-File: LICENSE
Keywords: Python,Shopify,TES
Requires-Python: >=3.9
Requires-Dist: python-tes~=0.3.19
Requires-Dist: requests==2.31.0
